{
    "ISS": [
        {
          "State": "AK",
          "Hispanic": 0.044915924,
          "NA": 0.035363013,
          "Asian": 0.016502897,
          "Pacific": 0.078270389,
          "Black": 0.086925961,
          "White": 0.026218359
        },
        {
          "State": "AL",
          "Hispanic": 0.041922473,
          "NA": 0.062443946,
          "Asian": 0.024083393,
          "Pacific": 0.059596845,
          "Black": 0.103742008,
          "White": 0.052395876
        },
        {
          "State": "AR",
          "Hispanic": 0.068739826,
          "NA": 0.085004236,
          "Asian": 0.033658659,
          "Pacific": 0.065697361,
          "Black": 0.176434726,
          "White": 0.067846225
        },
        {
          "State": "AZ",
          "Hispanic": 0.044197942,
          "NA": 0.063906374,
          "Asian": 0.021435401,
          "Pacific": 0.047694038,
          "Black": 0.08609096,
          "White": 0.031837519
        },
        {
          "State": "CA",
          "Hispanic": 0.010676674,
          "NA": 0.023934385,
          "Asian": 0.004129334,
          "Pacific": 0.018698126,
          "Black": 0.030584003,
          "White": 0.010451475
        },
        {
          "State": "CO",
          "Hispanic": 0.038350991,
          "NA": 0.048652384,
          "Asian": 0.012275799,
          "Pacific": 0.030337505,
          "Black": 0.071632488,
          "White": 0.020279417
        },
        {
          "State": "CT",
          "Hispanic": 0.059467475,
          "NA": 0.047283702,
          "Asian": 0.015326241,
          "Pacific": 0.021582734,
          "Black": 0.090116068,
          "White": 0.024081931
        },
        {
          "State": "DC",
          "Hispanic": 0.006038269,
          "NA": 0,
          "Asian": 0.007993605,
          "Pacific": 0,
          "Black": 0.020091513,
          "White": 0.003064953
        },
        {
          "State": "DE",
          "Hispanic": 0.045057284,
          "NA": 0.06259542,
          "Asian": 0.014534884,
          "Pacific": 0.011029412,
          "Black": 0.085280266,
          "White": 0.033570381
        },
        {
          "State": "FL",
          "Hispanic": 0.045461734,
          "NA": 0.076372998,
          "Asian": 0.021402144,
          "Pacific": 0.049927378,
          "Black": 0.092474778,
          "White": 0.044986589
        },
        {
          "State": "GA",
          "Hispanic": 0.064702057,
          "NA": 0.087581699,
          "Asian": 0.022130695,
          "Pacific": 0.087084871,
          "Black": 0.117736685,
          "White": 0.056601248
        },
        {
          "State": "HI",
          "Hispanic": 0.008865248,
          "NA": 0.024390244,
          "Asian": 0.004518072,
          "Pacific": 0.015451785,
          "Black": 0.017108168,
          "White": 0.009764626
        },
        {
          "State": "IA",
          "Hispanic": 0.031538192,
          "NA": 0.039175258,
          "Asian": 0.010873943,
          "Pacific": 0.039855072,
          "Black": 0.062199301,
          "White": 0.021434854
        },
        {
          "State": "ID",
          "Hispanic": 0.028774862,
          "NA": 0.035596572,
          "Asian": 0.014728288,
          "Pacific": 0.041958042,
          "Black": 0.052554316,
          "White": 0.019148435
        },
        {
          "State": "IL",
          "Hispanic": 0.041162162,
          "NA": 0.049071991,
          "Asian": 0.011232488,
          "Pacific": 0.024683339,
          "Black": 0.088116001,
          "White": 0.026396471
        },
        {
          "State": "IN",
          "Hispanic": 0.047595691,
          "NA": 0.042680894,
          "Asian": 0.01780298,
          "Pacific": 0.022140221,
          "Black": 0.080758632,
          "White": 0.032531339
        },
        {
          "State": "KS",
          "Hispanic": 0.054483212,
          "NA": 0.058385308,
          "Asian": 0.02044623,
          "Pacific": 0.037650602,
          "Black": 0.107596359,
          "White": 0.031239904
        },
        {
          "State": "KY",
          "Hispanic": 0.069662595,
          "NA": 0.088509317,
          "Asian": 0.025883176,
          "Pacific": 0.076525336,
          "Black": 0.160256498,
          "White": 0.065928979
        },
        {
          "State": "LA",
          "Hispanic": 0.067669173,
          "NA": 0.072453241,
          "Asian": 0.03788998,
          "Pacific": 0.043636364,
          "Black": 0.110992127,
          "White": 0.04710913
        },
        {
          "State": "MA",
          "Hispanic": 0.026258781,
          "NA": 0.02878684,
          "Asian": 0.009686168,
          "Pacific": 0.018544936,
          "Black": 0.035521391,
          "White": 0.012431853
        },
        {
          "State": "MD",
          "Hispanic": 0.007385451,
          "NA": 0.019764106,
          "Asian": 0.002446778,
          "Pacific": 0.020396601,
          "Black": 0.014906684,
          "White": 0.009924656
        },
        {
          "State": "ME",
          "Hispanic": 0.029509101,
          "NA": 0.035392089,
          "Asian": 0.013413343,
          "Pacific": 0.007407407,
          "Black": 0.062300319,
          "White": 0.017934786
        },
        {
          "State": "MI",
          "Hispanic": 0.027020754,
          "NA": 0.040801603,
          "Asian": 0.009006124,
          "Pacific": 0.018884892,
          "Black": 0.048221214,
          "White": 0.022022095
        },
        {
          "State": "MN",
          "Hispanic": 0.027112388,
          "NA": 0.046656012,
          "Asian": 0.01010738,
          "Pacific": 0.006504065,
          "Black": 0.057374567,
          "White": 0.016822371
        },
        {
          "State": "MO",
          "Hispanic": 0.082769591,
          "NA": 0.09239611,
          "Asian": 0.028888288,
          "Pacific": 0.082614943,
          "Black": 0.161310662,
          "White": 0.060558344
        },
        {
          "State": "MS",
          "Hispanic": 0.063806561,
          "NA": 0.155076495,
          "Asian": 0.036254906,
          "Pacific": 0.076142132,
          "Black": 0.130485178,
          "White": 0.069129208
        },
        {
          "State": "MT",
          "Hispanic": 0.038423806,
          "NA": 0.086747258,
          "Asian": 0.015278839,
          "Pacific": 0.025793651,
          "Black": 0.073202614,
          "White": 0.02782771
        },
        {
          "State": "NC",
          "Hispanic": 0.052610531,
          "NA": 0.066014011,
          "Asian": 0.018633149,
          "Pacific": 0.054471844,
          "Black": 0.094900662,
          "White": 0.042357696
        },
        {
          "State": "ND",
          "Hispanic": 0.021467278,
          "NA": 0.044548316,
          "Asian": 0.008251676,
          "Pacific": 0.022271715,
          "Black": 0.040127508,
          "White": 0.013297658
        },
        {
          "State": "NE",
          "Hispanic": 0.038490395,
          "NA": 0.065194751,
          "Asian": 0.014222008,
          "Pacific": 0.036363636,
          "Black": 0.056572304,
          "White": 0.024747963
        },
        {
          "State": "NH",
          "Hispanic": 0.048191554,
          "NA": 0.034334764,
          "Asian": 0.015418502,
          "Pacific": 0.036900369,
          "Black": 0.065821419,
          "White": 0.028092984
        },
        {
          "State": "NJ",
          "Hispanic": 0.039189708,
          "NA": 0.023172193,
          "Asian": 0.008385557,
          "Pacific": 0.009950249,
          "Black": 0.061369008,
          "White": 0.015418106
        },
        {
          "State": "NM",
          "Hispanic": 0.032731731,
          "NA": 0.049920491,
          "Asian": 0.018060837,
          "Pacific": 0.017830609,
          "Black": 0.061068702,
          "White": 0.027169248
        },
        {
          "State": "NV",
          "Hispanic": 0.037134345,
          "NA": 0.053608247,
          "Asian": 0.011965613,
          "Pacific": 0.034892465,
          "Black": 0.069205204,
          "White": 0.027639069
        },
        {
          "State": "NY",
          "Hispanic": 0.022084311,
          "NA": 0.039991636,
          "Asian": 0.00905235,
          "Pacific": 0.007526342,
          "Black": 0.047436802,
          "White": 0.0251541
        },
        {
          "State": "OH",
          "Hispanic": 0.037509689,
          "NA": 0.037514654,
          "Asian": 0.015309784,
          "Pacific": 0.020058504,
          "Black": 0.08152447,
          "White": 0.024212274
        },
        {
          "State": "OK",
          "Hispanic": 0.054761517,
          "NA": 0.053220624,
          "Asian": 0.019476786,
          "Pacific": 0.078957033,
          "Black": 0.118968893,
          "White": 0.046330367
        },
        {
          "State": "OR",
          "Hispanic": 0.034352653,
          "NA": 0.049206714,
          "Asian": 0.00814029,
          "Pacific": 0.057666814,
          "Black": 0.045526467,
          "White": 0.023409619
        },
        {
          "State": "PA",
          "Hispanic": 0.044163194,
          "NA": 0.037143604,
          "Asian": 0.009175175,
          "Pacific": 0.016477858,
          "Black": 0.044241814,
          "White": 0.021200329
        },
        {
          "State": "RI",
          "Hispanic": 0.031575855,
          "NA": 0.051121076,
          "Asian": 0.013549534,
          "Pacific": 0.013157895,
          "Black": 0.037727957,
          "White": 0.026032743
        },
        {
          "State": "SC",
          "Hispanic": 0.069091983,
          "NA": 0.112908444,
          "Asian": 0.035842593,
          "Pacific": 0.075679647,
          "Black": 0.145659915,
          "White": 0.067619532
        },
        {
          "State": "SD",
          "Hispanic": 0.043557679,
          "NA": 0.114593409,
          "Asian": 0.021013597,
          "Pacific": 0.056497175,
          "Black": 0.071272197,
          "White": 0.026891729
        },
        {
          "State": "TN",
          "Hispanic": 0.058475237,
          "NA": 0.080082136,
          "Asian": 0.027525305,
          "Pacific": 0.05862069,
          "Black": 0.125314817,
          "White": 0.060437948
        },
        {
          "State": "TX",
          "Hispanic": 0.072433823,
          "NA": 0.089589017,
          "Asian": 0.022715953,
          "Pacific": 0.086833822,
          "Black": 0.139952243,
          "White": 0.056373662
        },
        {
          "State": "UT",
          "Hispanic": 0.01277418,
          "NA": 0.015036593,
          "Asian": 0.004384042,
          "Pacific": 0.010829627,
          "Black": 0.026237833,
          "White": 0.006184965
        },
        {
          "State": "VA",
          "Hispanic": 0.031926512,
          "NA": 0.056808134,
          "Asian": 0.010733975,
          "Pacific": 0.028385117,
          "Black": 0.081089797,
          "White": 0.031044852
        },
        {
          "State": "VT",
          "Hispanic": 0.023019634,
          "NA": 0.031496063,
          "Asian": 0.008717949,
          "Pacific": 0,
          "Black": 0.057291667,
          "White": 0.022587406
        },
        {
          "State": "WA",
          "Hispanic": 0.025234555,
          "NA": 0.049637778,
          "Asian": 0.010660638,
          "Pacific": 0.041614648,
          "Black": 0.041465198,
          "White": 0.018458786
        },
        {
          "State": "WI",
          "Hispanic": 0.023685145,
          "NA": 0.04563245,
          "Asian": 0.009219073,
          "Pacific": 0.014851485,
          "Black": 0.044210348,
          "White": 0.016471778
        },
        {
          "State": "WV",
          "Hispanic": 0.067670814,
          "NA": 0.051643192,
          "Asian": 0.03685259,
          "Pacific": 0.009174312,
          "Black": 0.130955231,
          "White": 0.059176003
        },
        {
          "State": "WY",
          "Hispanic": 0.039700491,
          "NA": 0.099177937,
          "Asian": 0.031425365,
          "Pacific": 0.023255814,
          "Black": 0.053674649,
          "White": 0.029712563
        }
      ],
    "OOS":[
        {
          "State": "AK",
          "Hispanic": 0.043335967,
          "NA": 0.074834994,
          "Asian": 0.015369111,
          "Pacific": 0.075533662,
          "Black": 0.087394564,
          "White": 0.025392084
        },
        {
          "State": "AL",
          "Hispanic": 0.028113886,
          "NA": 0.046076233,
          "Asian": 0.018511862,
          "Pacific": 0.040315513,
          "Black": 0.135902832,
          "White": 0.034562223
        },
        {
          "State": "AR",
          "Hispanic": 0.036601943,
          "NA": 0.050550692,
          "Asian": 0.014764765,
          "Pacific": 0.044695746,
          "Black": 0.136949277,
          "White": 0.035200691
        },
        {
          "State": "AZ",
          "Hispanic": 0.044903998,
          "NA": 0.081664298,
          "Asian": 0.021373716,
          "Pacific": 0.049943757,
          "Black": 0.107340422,
          "White": 0.031224359
        },
        {
          "State": "CA",
          "Hispanic": 0.027604097,
          "NA": 0.06914378,
          "Asian": 0.011093455,
          "Pacific": 0.048120862,
          "Black": 0.080722115,
          "White": 0.023780153
        },
        {
          "State": "CO",
          "Hispanic": 0.048912084,
          "NA": 0.085832757,
          "Asian": 0.019068171,
          "Pacific": 0.058399697,
          "Black": 0.090855022,
          "White": 0.027498002
        },
        {
          "State": "CT",
          "Hispanic": 0.04220011,
          "NA": 0.036217304,
          "Asian": 0.008890708,
          "Pacific": 0.019184652,
          "Black": 0.075886453,
          "White": 0.011294445
        },
        {
          "State": "DC",
          "Hispanic": 0.027917189,
          "NA": 0.02970297,
          "Asian": 0.019184652,
          "Pacific": 0.071942446,
          "Black": 0.083875185,
          "White": 0.007426618
        },
        {
          "State": "DE",
          "Hispanic": 0.05357062,
          "NA": 0.076335878,
          "Asian": 0.019767442,
          "Pacific": 0.029411765,
          "Black": 0.116562009,
          "White": 0.031820117
        },
        {
          "State": "FL",
          "Hispanic": 0.030231211,
          "NA": 0.060640732,
          "Asian": 0.013124848,
          "Pacific": 0.038852578,
          "Black": 0.07999305,
          "White": 0.032181061
        },
        {
          "State": "GA",
          "Hispanic": 0.03715286,
          "NA": 0.05620915,
          "Asian": 0.014415544,
          "Pacific": 0.071217712,
          "Black": 0.105861134,
          "White": 0.026611446
        },
        {
          "State": "HI",
          "Hispanic": 0.025686488,
          "NA": 0.054878049,
          "Asian": 0.01789084,
          "Pacific": 0.046463158,
          "Black": 0.041390728,
          "White": 0.022641992
        },
        {
          "State": "IA",
          "Hispanic": 0.02667419,
          "NA": 0.032989691,
          "Asian": 0.011759968,
          "Pacific": 0.026086957,
          "Black": 0.078259666,
          "White": 0.015233818
        },
        {
          "State": "ID",
          "Hispanic": 0.022988506,
          "NA": 0.043726653,
          "Asian": 0.008125952,
          "Pacific": 0.02952603,
          "Black": 0.04374633,
          "White": 0.015498362
        },
        {
          "State": "IL",
          "Hispanic": 0.025309755,
          "NA": 0.04091676,
          "Asian": 0.007076879,
          "Pacific": 0.028905489,
          "Black": 0.088070493,
          "White": 0.01774956
        },
        {
          "State": "IN",
          "Hispanic": 0.046422002,
          "NA": 0.048016005,
          "Asian": 0.017143611,
          "Pacific": 0.022140221,
          "Black": 0.142756753,
          "White": 0.028015338
        },
        {
          "State": "KS",
          "Hispanic": 0.039185712,
          "NA": 0.058385308,
          "Asian": 0.01922663,
          "Pacific": 0.030120482,
          "Black": 0.12015395,
          "White": 0.022510923
        },
        {
          "State": "KY",
          "Hispanic": 0.035703898,
          "NA": 0.040372671,
          "Asian": 0.014253235,
          "Pacific": 0.039296794,
          "Black": 0.107712711,
          "White": 0.030609949
        },
        {
          "State": "LA",
          "Hispanic": 0.047424462,
          "NA": 0.066460868,
          "Asian": 0.02589728,
          "Pacific": 0.043636364,
          "Black": 0.099266103,
          "White": 0.037431955
        },
        {
          "State": "MA",
          "Hispanic": 0.042351554,
          "NA": 0.026730637,
          "Asian": 0.008330105,
          "Pacific": 0.018544936,
          "Black": 0.055953001,
          "White": 0.013325361
        },
        {
          "State": "MD",
          "Hispanic": 0.021257932,
          "NA": 0.047178833,
          "Asian": 0.006393771,
          "Pacific": 0.029461756,
          "Black": 0.053475437,
          "White": 0.016607006
        },
        {
          "State": "ME",
          "Hispanic": 0.031991175,
          "NA": 0.045801527,
          "Asian": 0.013413343,
          "Pacific": 0.007407407,
          "Black": 0.051757188,
          "White": 0.020916639
        },
        {
          "State": "MI",
          "Hispanic": 0.060316894,
          "NA": 0.074709419,
          "Asian": 0.017071609,
          "Pacific": 0.03147482,
          "Black": 0.158340826,
          "White": 0.03415478
        },
        {
          "State": "MN",
          "Hispanic": 0.035248704,
          "NA": 0.071612983,
          "Asian": 0.012186808,
          "Pacific": 0.009756098,
          "Black": 0.096280277,
          "White": 0.013770078
        },
        {
          "State": "MO",
          "Hispanic": 0.041247669,
          "NA": 0.047303271,
          "Asian": 0.013145794,
          "Pacific": 0.042385057,
          "Black": 0.129872221,
          "White": 0.026387123
        },
        {
          "State": "MS",
          "Hispanic": 0.046231101,
          "NA": 0.07162726,
          "Asian": 0.027471501,
          "Pacific": 0.025380711,
          "Black": 0.130542518,
          "White": 0.037875635
        },
        {
          "State": "MT",
          "Hispanic": 0.037115762,
          "NA": 0.107510634,
          "Asian": 0.006111536,
          "Pacific": 0.011904762,
          "Black": 0.064052288,
          "White": 0.020748806
        },
        {
          "State": "NC",
          "Hispanic": 0.045174497,
          "NA": 0.100637686,
          "Asian": 0.016345972,
          "Pacific": 0.052999632,
          "Black": 0.108897766,
          "White": 0.03105485
        },
        {
          "State": "ND",
          "Hispanic": 0.020842018,
          "NA": 0.057617094,
          "Asian": 0.006188757,
          "Pacific": 0.026726058,
          "Black": 0.039752485,
          "White": 0.012178947
        },
        {
          "State": "NE",
          "Hispanic": 0.034459896,
          "NA": 0.072693189,
          "Asian": 0.017717247,
          "Pacific": 0.039393939,
          "Black": 0.105977281,
          "White": 0.019877826
        },
        {
          "State": "NH",
          "Hispanic": 0.070620327,
          "NA": 0.054363376,
          "Asian": 0.017790579,
          "Pacific": 0.022140221,
          "Black": 0.103318047,
          "White": 0.026192241
        },
        {
          "State": "NJ",
          "Hispanic": 0.038378155,
          "NA": 0.023971235,
          "Asian": 0.009307374,
          "Pacific": 0.021995287,
          "Black": 0.086307625,
          "White": 0.014163672
        },
        {
          "State": "NM",
          "Hispanic": 0.036950509,
          "NA": 0.052447751,
          "Asian": 0.018536122,
          "Pacific": 0.023774146,
          "Black": 0.081232896,
          "White": 0.028861106
        },
        {
          "State": "NV",
          "Hispanic": 0.058259956,
          "NA": 0.075670103,
          "Asian": 0.027919765,
          "Pacific": 0.070988119,
          "Black": 0.148948243,
          "White": 0.037775891
        },
        {
          "State": "NY",
          "Hispanic": 0.01769105,
          "NA": 0.030268179,
          "Asian": 0.005805222,
          "Pacific": 0.007902659,
          "Black": 0.049651102,
          "White": 0.01795962
        },
        {
          "State": "OH",
          "Hispanic": 0.060112113,
          "NA": 0.052754982,
          "Asian": 0.017515881,
          "Pacific": 0.03343084,
          "Black": 0.146169362,
          "White": 0.027688164
        },
        {
          "State": "OK",
          "Hispanic": 0.044245784,
          "NA": 0.041089525,
          "Asian": 0.015092712,
          "Pacific": 0.049944914,
          "Black": 0.120862894,
          "White": 0.033371484
        },
        {
          "State": "OR",
          "Hispanic": 0.032469998,
          "NA": 0.074959761,
          "Asian": 0.012946525,
          "Pacific": 0.051038445,
          "Black": 0.067894131,
          "White": 0.025163685
        },
        {
          "State": "PA",
          "Hispanic": 0.064161412,
          "NA": 0.05754643,
          "Asian": 0.013990182,
          "Pacific": 0.020597322,
          "Black": 0.125257515,
          "White": 0.019894596
        },
        {
          "State": "RI",
          "Hispanic": 0.053429285,
          "NA": 0.104932735,
          "Asian": 0.021101733,
          "Pacific": 0.013157895,
          "Black": 0.076459762,
          "White": 0.023795926
        },
        {
          "State": "SC",
          "Hispanic": 0.051624734,
          "NA": 0.098350049,
          "Asian": 0.024981201,
          "Pacific": 0.067597355,
          "Black": 0.139626664,
          "White": 0.046787623
        },
        {
          "State": "SD",
          "Hispanic": 0.036532247,
          "NA": 0.075127362,
          "Asian": 0.012360939,
          "Pacific": 0.04519774,
          "Black": 0.054731209,
          "White": 0.014661201
        },
        {
          "State": "TN",
          "Hispanic": 0.042860323,
          "NA": 0.062833676,
          "Asian": 0.019365834,
          "Pacific": 0.044137931,
          "Black": 0.154739101,
          "White": 0.029058717
        },
        {
          "State": "TX",
          "Hispanic": 0.036079511,
          "NA": 0.043122415,
          "Asian": 0.009593766,
          "Pacific": 0.037555628,
          "Black": 0.097386877,
          "White": 0.018706402
        },
        {
          "State": "UT",
          "Hispanic": 0.023039976,
          "NA": 0.026081171,
          "Asian": 0.010258658,
          "Pacific": 0.026687295,
          "Black": 0.046233601,
          "White": 0.009142387
        },
        {
          "State": "VA",
          "Hispanic": 0.031840005,
          "NA": 0.063218391,
          "Asian": 0.009180527,
          "Pacific": 0.044495589,
          "Black": 0.101338484,
          "White": 0.025488192
        },
        {
          "State": "VT",
          "Hispanic": 0.036560596,
          "NA": 0.076771654,
          "Asian": 0.017948718,
          "Pacific": 0.014705882,
          "Black": 0.080965909,
          "White": 0.02189323
        },
        {
          "State": "WA",
          "Hispanic": 0.035884926,
          "NA": 0.066206064,
          "Asian": 0.013205356,
          "Pacific": 0.067082813,
          "Black": 0.06700256,
          "White": 0.022708173
        },
        {
          "State": "WI",
          "Hispanic": 0.035005325,
          "NA": 0.0643124,
          "Asian": 0.013619085,
          "Pacific": 0.02640264,
          "Black": 0.122011831,
          "White": 0.015518678
        },
        {
          "State": "WV",
          "Hispanic": 0.057192753,
          "NA": 0.046948357,
          "Asian": 0.023904382,
          "Pacific": 0.027522936,
          "Black": 0.142446732,
          "White": 0.055853244
        },
        {
          "State": "WY",
          "Hispanic": 0.035410654,
          "NA": 0.077963405,
          "Asian": 0.022446689,
          "Pacific": 0.031007752,
          "Black": 0.061106524,
          "White": 0.021894176
        }
      ],

    "TRANSF":[
        {
          "State": "AK",
          "Hispanic": 0,
          "NA": 0,
          "Asian": 0,
          "Pacific": 0,
          "Black": 0.000468604,
          "White": 0.0000317798
        },
        {
          "State": "AL",
          "Hispanic": 0.001748425,
          "NA": 0.002690583,
          "Asian": 0.001078361,
          "Pacific": 0.003505697,
          "Black": 0.006433768,
          "White": 0.00267928
        },
        {
          "State": "AR",
          "Hispanic": 0.000201386,
          "NA": 0,
          "Asian": 0,
          "Pacific": 0,
          "Black": 0.001524142,
          "White": 0.000358852
        },
        {
          "State": "AZ",
          "Hispanic": 0.000128915,
          "NA": 0.000719916,
          "Asian": 0,
          "Pacific": 0.000449944,
          "Black": 0.0000993739,
          "White": 0.0000557419
        },
        {
          "State": "CA",
          "Hispanic": 0.000413563,
          "NA": 0.001491239,
          "Asian": 0.000155173,
          "Pacific": 0.000466287,
          "Black": 0.001097257,
          "White": 0.000384245
        },
        {
          "State": "CO",
          "Hispanic": 0.000209823,
          "NA": 0.000276434,
          "Asian": 0,
          "Pacific": 0,
          "Black": 0,
          "White": 0.000209532
        },
        {
          "State": "CT",
          "Hispanic": 0.00041325,
          "NA": 0,
          "Asian": 0.000223198,
          "Pacific": 0,
          "Black": 0.000463694,
          "White": 0.000109978
        },
        {
          "State": "DC",
          "Hispanic": 0.000156838,
          "NA": 0,
          "Asian": 0,
          "Pacific": 0,
          "Black": 0.001513744,
          "White": 0
        },
        {
          "State": "DE",
          "Hispanic": 0.001267944,
          "NA": 0,
          "Asian": 0.000387597,
          "Pacific": 0,
          "Black": 0.003439837,
          "White": 0.000961857
        },
        {
          "State": "FL",
          "Hispanic": 0.000590516,
          "NA": 0.000381388,
          "Asian": 0,
          "Pacific": 0,
          "Black": 0.001466563,
          "White": 0.000533716
        },
        {
          "State": "GA",
          "Hispanic": 0.002196458,
          "NA": 0.004793028,
          "Asian": 0.00086553,
          "Pacific": 0.001476015,
          "Black": 0.004427134,
          "White": 0.002253617
        },
        {
          "State": "HI",
          "Hispanic": 0.000272777,
          "NA": 0,
          "Asian": 0.000145159,
          "Pacific": 0.000503081,
          "Black": 0,
          "White": 0.0000852806
        },
        {
          "State": "IA",
          "Hispanic": 0.000719872,
          "NA": 0,
          "Asian": 0,
          "Pacific": 0.001449275,
          "Black": 0.002284448,
          "White": 0.00022119
        },
        {
          "State": "ID",
          "Hispanic": 0.000156918,
          "NA": 0,
          "Asian": 0,
          "Pacific": 0,
          "Black": 0.000587199,
          "White": 0.0000444589
        },
        {
          "State": "IL",
          "Hispanic": 0.000597001,
          "NA": 0.00056243,
          "Asian": 0.000205723,
          "Pacific": 0.000649562,
          "Black": 0.002474529,
          "White": 0.000670977
        },
        {
          "State": "IN",
          "Hispanic": 0.000569326,
          "NA": 0.000666889,
          "Asian": 0.000175832,
          "Pacific": 0,
          "Black": 0.001358084,
          "White": 0.000550766
        },
        {
          "State": "KS",
          "Hispanic": 0.000925816,
          "NA": 0.000693001,
          "Asian": 0.000286965,
          "Pacific": 0.003012048,
          "Black": 0.010225868,
          "White": 0.000313654
        },
        {
          "State": "KY",
          "Hispanic": 0.002326934,
          "NA": 0.00310559,
          "Asian": 0.000174886,
          "Pacific": 0.002068252,
          "Black": 0.005428021,
          "White": 0.002084042
        },
        {
          "State": "LA",
          "Hispanic": 0.002405081,
          "NA": 0.003268567,
          "Asian": 0.001042843,
          "Pacific": 0.002424242,
          "Black": 0.007263603,
          "White": 0.002104657
        },
        {
          "State": "MA",
          "Hispanic": 0.000519687,
          "NA": 0,
          "Asian": 0,
          "Pacific": 0,
          "Black": 0.000544843,
          "White": 0.000127644
        },
        {
          "State": "MD",
          "Hispanic": 0.000162706,
          "NA": 0,
          "Asian": 0.0000357194,
          "Pacific": 0,
          "Black": 0.000418456,
          "White": 0.0000465264
        },
        {
          "State": "ME",
          "Hispanic": 0,
          "NA": 0,
          "Asian": 0,
          "Pacific": 0,
          "Black": 0,
          "White": 0.0000124764
        },
        {
          "State": "MI",
          "Hispanic": 0.000124972,
          "NA": 0.000160321,
          "Asian": 0,
          "Pacific": 0,
          "Black": 0.000161203,
          "White": 0.000108422
        },
        {
          "State": "MN",
          "Hispanic": 0.000415914,
          "NA": 0.001106467,
          "Asian": 0.000034089,
          "Pacific": 0,
          "Black": 0.00116782,
          "White": 0.0000976601
        },
        {
          "State": "MO",
          "Hispanic": 0.000292537,
          "NA": 0.000442087,
          "Asian": 0.000216392,
          "Pacific": 0,
          "Black": 0.002340946,
          "White": 0.000255753
        },
        {
          "State": "MS",
          "Hispanic": 0.002892855,
          "NA": 0.002781641,
          "Asian": 0.000747524,
          "Pacific": 0,
          "Black": 0.007212543,
          "White": 0.003077796
        },
        {
          "State": "MT",
          "Hispanic": 0,
          "NA": 0,
          "Asian": 0,
          "Pacific": 0,
          "Black": 0,
          "White": 0.0000171195
        },
        {
          "State": "NC",
          "Hispanic": 0.000399914,
          "NA": 0.00017963,
          "Asian": 0,
          "Pacific": 0.001472212,
          "Black": 0.000722867,
          "White": 0.000192588
        },
        {
          "State": "ND",
          "Hispanic": 0,
          "NA": 0.00038157,
          "Asian": 0.00103146,
          "Pacific": 0,
          "Black": 0.001500094,
          "White": 0.000196063
        },
        {
          "State": "NE",
          "Hispanic": 0.001116675,
          "NA": 0.002916059,
          "Asian": 0,
          "Pacific": 0,
          "Black": 0.005274071,
          "White": 0.000345864
        },
        {
          "State": "NH",
          "Hispanic": 0.000404122,
          "NA": 0.00286123,
          "Asian": 0,
          "Pacific": 0,
          "Black": 0.00053952,
          "White": 0.000114045
        },
        {
          "State": "NJ",
          "Hispanic": 0.000209341,
          "NA": 0,
          "Asian": 0.000014868,
          "Pacific": 0,
          "Black": 0.000587439,
          "White": 0.0000845686
        },
        {
          "State": "NM",
          "Hispanic": 0.000197906,
          "NA": 0.000454339,
          "Asian": 0,
          "Pacific": 0,
          "Black": 0,
          "White": 0.0000995211
        },
        {
          "State": "NV",
          "Hispanic": 0.003540491,
          "NA": 0.003298969,
          "Asian": 0.002362144,
          "Pacific": 0.006918334,
          "Black": 0.011551088,
          "White": 0.002078548
        },
        {
          "State": "NY",
          "Hispanic": 0.0000767754,
          "NA": 0.000522766,
          "Asian": 0.0000330077,
          "Pacific": 0,
          "Black": 0.000397492,
          "White": 0.000261707
        },
        {
          "State": "OH",
          "Hispanic": 0.000449352,
          "NA": 0.000586166,
          "Asian": 0.000159477,
          "Pacific": 0,
          "Black": 0.00784175,
          "White": 0.000249807
        },
        {
          "State": "OK",
          "Hispanic": 0.000661196,
          "NA": 0.001127095,
          "Asian": 0.00043122,
          "Pacific": 0.000734484,
          "Black": 0.000866746,
          "White": 0.000635211
        },
        {
          "State": "OR",
          "Hispanic": 0.000418368,
          "NA": 0.000459876,
          "Asian": 0.000173198,
          "Pacific": 0.000441891,
          "Black": 0.000287687,
          "White": 0.000170994
        },
        {
          "State": "PA",
          "Hispanic": 0.000707458,
          "NA": 0.001046299,
          "Asian": 0.000125472,
          "Pacific": 0,
          "Black": 0.002383962,
          "White": 0.000469342
        },
        {
          "State": "RI",
          "Hispanic": 0.000646204,
          "NA": 0.007174888,
          "Asian": 0,
          "Pacific": 0,
          "Black": 0.001003848,
          "White": 0.0000713878
        },
        {
          "State": "SC",
          "Hispanic": 0.001942532,
          "NA": 0.002588159,
          "Asian": 0.000167098,
          "Pacific": 0,
          "Black": 0.004732851,
          "White": 0.00174422
        },
        {
          "State": "SD",
          "Hispanic": 0,
          "NA": 0.000386922,
          "Asian": 0,
          "Pacific": 0,
          "Black": 0.0004865,
          "White": 0.000135037
        },
        {
          "State": "TN",
          "Hispanic": 0.003472454,
          "NA": 0.006570842,
          "Asian": 0.001652551,
          "Pacific": 0.00137931,
          "Black": 0.010464333,
          "White": 0.002996227
        },
        {
          "State": "TX",
          "Hispanic": 0.002150501,
          "NA": 0.002640148,
          "Asian": 0.000539969,
          "Pacific": 0.002170846,
          "Black": 0.003554748,
          "White": 0.001492271
        },
        {
          "State": "UT",
          "Hispanic": 0.00029729,
          "NA": 0.000532269,
          "Asian": 0.000175362,
          "Pacific": 0.00154709,
          "Black": 0.001269573,
          "White": 0.00026019
        },
        {
          "State": "VA",
          "Hispanic": 0.000227081,
          "NA": 0.000442087,
          "Asian": 0,
          "Pacific": 0.005370157,
          "Black": 0.001476644,
          "White": 0.000545647
        },
        {
          "State": "VT",
          "Hispanic": 0,
          "NA": 0,
          "Asian": 0,
          "Pacific": 0,
          "Black": 0,
          "White": 0.000133495
        },
        {
          "State": "WA",
          "Hispanic": 0.000395804,
          "NA": 0.000804937,
          "Asian": 0.000358237,
          "Pacific": 0.000332917,
          "Black": 0.000467271,
          "White": 0.000586461
        },
        {
          "State": "WI",
          "Hispanic": 0.00051732,
          "NA": 0.000177904,
          "Asian": 0,
          "Pacific": 0,
          "Black": 0.003636716,
          "White": 0.0000972551
        },
        {
          "State": "WV",
          "Hispanic": 0.002619515,
          "NA": 0.004694836,
          "Asian": 0,
          "Pacific": 0,
          "Black": 0.005745751,
          "White": 0.001754448
        },
        {
          "State": "WY",
          "Hispanic": 0,
          "NA": 0,
          "Asian": 0,
          "Pacific": 0,
          "Black": 0,
          "White": 0.0000269136
        }
      ],
    "EXP":[
        {
          "State": "AK",
          "Hispanic": 0.000225708,
          "NA": 0.0000647082,
          "Asian": 0,
          "Pacific": 0,
          "Black": 0.001405811,
          "White": 0.0000635597
        },
        {
          "State": "AL",
          "Hispanic": 0.00103316,
          "NA": 0.000896861,
          "Asian": 0,
          "Pacific": 0.003505697,
          "Black": 0.000885896,
          "White": 0.000768963
        },
        {
          "State": "AR",
          "Hispanic": 0.001258664,
          "NA": 0.001129624,
          "Asian": 0.000500501,
          "Pacific": 0.001615509,
          "Black": 0.002154121,
          "White": 0.001129718
        },
        {
          "State": "AZ",
          "Hispanic": 0.000325262,
          "NA": 0.000406106,
          "Asian": 0.000370108,
          "Pacific": 0,
          "Black": 0.000861241,
          "White": 0.000329992
        },
        {
          "State": "CA",
          "Hispanic": 0.000298274,
          "NA": 0.001565801,
          "Asian": 0.000123564,
          "Pacific": 0.00149212,
          "Black": 0.000690562,
          "White": 0.000425982
        },
        {
          "State": "CO",
          "Hispanic": 0.000439629,
          "NA": 0.000276434,
          "Asian": 0.000283016,
          "Pacific": 0.001516875,
          "Black": 0.000523386,
          "White": 0.00034922
        },
        {
          "State": "CT",
          "Hispanic": 0.0002755,
          "NA": 0,
          "Asian": 0,
          "Pacific": 0,
          "Black": 0.000623089,
          "White": 0.0000966477
        },
        {
          "State": "DC",
          "Hispanic": 0,
          "NA": 0,
          "Asian": 0,
          "Pacific": 0,
          "Black": 0.000584856,
          "White": 0
        },
        {
          "State": "DE",
          "Hispanic": 0,
          "NA": 0,
          "Asian": 0,
          "Pacific": 0,
          "Black": 0.000415551,
          "White": 0.000157681
        },
        {
          "State": "FL",
          "Hispanic": 0.0000614409,
          "NA": 0.000381388,
          "Asian": 0.0000270059,
          "Pacific": 0.000363108,
          "Black": 0.00021839,
          "White": 0.000122462
        },
        {
          "State": "GA",
          "Hispanic": 0.000405021,
          "NA": 0.001742919,
          "Asian": 0.000208921,
          "Pacific": 0.001476015,
          "Black": 0.001471632,
          "White": 0.000463696
        },
        {
          "State": "HI",
          "Hispanic": 0,
          "NA": 0,
          "Asian": 0,
          "Pacific": 0,
          "Black": 0,
          "White": 0
        },
        {
          "State": "IA",
          "Hispanic": 0.00038912,
          "NA": 0,
          "Asian": 0.000161095,
          "Pacific": 0,
          "Black": 0.000761483,
          "White": 0.000262342
        },
        {
          "State": "ID",
          "Hispanic": 0.00082382,
          "NA": 0,
          "Asian": 0,
          "Pacific": 0.001554002,
          "Black": 0,
          "White": 0.000466818
        },
        {
          "State": "IL",
          "Hispanic": 0.000115923,
          "NA": 0.00056243,
          "Asian": 0.0000411446,
          "Pacific": 0,
          "Black": 0.000423799,
          "White": 0.000163702
        },
        {
          "State": "IN",
          "Hispanic": 0.003232022,
          "NA": 0.003334445,
          "Asian": 0.000747286,
          "Pacific": 0,
          "Black": 0.005448128,
          "White": 0.002532688
        },
        {
          "State": "KS",
          "Hispanic": 0.001098061,
          "NA": 0.002772003,
          "Asian": 0.000430447,
          "Pacific": 0,
          "Black": 0.002163164,
          "White": 0.00096919
        },
        {
          "State": "KY",
          "Hispanic": 0,
          "NA": 0,
          "Asian": 0,
          "Pacific": 0,
          "Black": 0.000109381,
          "White": 0.0000725046
        },
        {
          "State": "LA",
          "Hispanic": 0.000373605,
          "NA": 0.000363174,
          "Asian": 0.000347614,
          "Pacific": 0,
          "Black": 0.000587243,
          "White": 0.000221383
        },
        {
          "State": "MA",
          "Hispanic": 0.0000350351,
          "NA": 0,
          "Asian": 0,
          "Pacific": 0,
          "Black": 0.000118444,
          "White": 0.0000655015
        },
        {
          "State": "MD",
          "Hispanic": 0,
          "NA": 0,
          "Asian": 0,
          "Pacific": 0,
          "Black": 0,
          "White": 0.0000058158
        },
        {
          "State": "ME",
          "Hispanic": 0.000551572,
          "NA": 0.001387925,
          "Asian": 0,
          "Pacific": 0,
          "Black": 0.000638978,
          "White": 0.000636295
        },
        {
          "State": "MI",
          "Hispanic": 0.000714126,
          "NA": 0.001122244,
          "Asian": 0.000280191,
          "Pacific": 0.000899281,
          "Black": 0.001368435,
          "White": 0.000548825
        },
        {
          "State": "MN",
          "Hispanic": 0.000259946,
          "NA": 0.000245881,
          "Asian": 0.000136356,
          "Pacific": 0.001626016,
          "Black": 0.000464965,
          "White": 0.000175457
        },
        {
          "State": "MO",
          "Hispanic": 0.000182835,
          "NA": 0.000884173,
          "Asian": 0,
          "Pacific": 0.000718391,
          "Black": 0.000261596,
          "White": 0.000300361
        },
        {
          "State": "MS",
          "Hispanic": 0.00076415,
          "NA": 0.001390821,
          "Asian": 0,
          "Pacific": 0,
          "Black": 0.001806207,
          "White": 0.000576229
        },
        {
          "State": "MT",
          "Hispanic": 0,
          "NA": 0.002238639,
          "Asian": 0,
          "Pacific": 0,
          "Black": 0,
          "White": 0.000453666
        },
        {
          "State": "NC",
          "Hispanic": 0.000245492,
          "NA": 0.001032872,
          "Asian": 0.0000419666,
          "Pacific": 0,
          "Black": 0.000667839,
          "White": 0.000182178
        },
        {
          "State": "ND",
          "Hispanic": 0.00041684,
          "NA": 0.001240103,
          "Asian": 0.00103146,
          "Pacific": 0,
          "Black": 0,
          "White": 0.000138397
        },
        {
          "State": "NE",
          "Hispanic": 0.0000697922,
          "NA": 0.003332639,
          "Asian": 0,
          "Pacific": 0,
          "Black": 0.0000901551,
          "White": 0.0000373907
        },
        {
          "State": "NH",
          "Hispanic": 0.000202061,
          "NA": 0,
          "Asian": 0,
          "Pacific": 0.007380074,
          "Black": 0,
          "White": 0.000240761
        },
        {
          "State": "NJ",
          "Hispanic": 0.000106104,
          "NA": 0,
          "Asian": 0,
          "Pacific": 0,
          "Black": 0.000275362,
          "White": 0.000263102
        },
        {
          "State": "NM",
          "Hispanic": 0.000386158,
          "NA": 0.004174239,
          "Asian": 0.000475285,
          "Pacific": 0,
          "Black": 0.00057612,
          "White": 0.000485165
        },
        {
          "State": "NV",
          "Hispanic": 0.0000918283,
          "NA": 0.000412371,
          "Asian": 0,
          "Pacific": 0.000300797,
          "Black": 0.000243181,
          "White": 0.000156047
        },
        {
          "State": "NY",
          "Hispanic": 0.0000526054,
          "NA": 0.000104553,
          "Asian": 0.0000330077,
          "Pacific": 0,
          "Black": 0.000106137,
          "White": 0.0000899617
        },
        {
          "State": "OH",
          "Hispanic": 0.002853388,
          "NA": 0.001172333,
          "Asian": 0.000797385,
          "Pacific": 0.001671542,
          "Black": 0.004621537,
          "White": 0.001289481
        },
        {
          "State": "OK",
          "Hispanic": 0.000389472,
          "NA": 0.000810717,
          "Asian": 0.00028748,
          "Pacific": 0,
          "Black": 0.000658085,
          "White": 0.000486423
        },
        {
          "State": "OR",
          "Hispanic": 0.000689532,
          "NA": 0.001379628,
          "Asian": 0.0000865988,
          "Pacific": 0.001767565,
          "Black": 0.000791139,
          "White": 0.000410937
        },
        {
          "State": "PA",
          "Hispanic": 0.000501348,
          "NA": 0,
          "Asian": 0.0000313681,
          "Pacific": 0,
          "Black": 0.000452602,
          "White": 0.000101433
        },
        {
          "State": "RI",
          "Hispanic": 0,
          "NA": 0,
          "Asian": 0,
          "Pacific": 0,
          "Black": 0,
          "White": 0
        },
        {
          "State": "SC",
          "Hispanic": 0.000777013,
          "NA": 0.001941119,
          "Asian": 0.000167098,
          "Pacific": 0.007347539,
          "Black": 0.00259702,
          "White": 0.001103744
        },
        {
          "State": "SD",
          "Hispanic": 0,
          "NA": 0.001031792,
          "Asian": 0,
          "Pacific": 0,
          "Black": 0,
          "White": 0.0000964553
        },
        {
          "State": "TN",
          "Hispanic": 0.001179744,
          "NA": 0.00164271,
          "Asian": 0.000309853,
          "Pacific": 0.004137931,
          "Black": 0.003454117,
          "White": 0.000596124
        },
        {
          "State": "TX",
          "Hispanic": 0.000193405,
          "NA": 0.000440025,
          "Asian": 0.0000186196,
          "Pacific": 0,
          "Black": 0.000258309,
          "White": 0.00015042
        },
        {
          "State": "UT",
          "Hispanic": 0.000315871,
          "NA": 0.000798403,
          "Asian": 0,
          "Pacific": 0,
          "Black": 0.000634786,
          "White": 0.000158894
        },
        {
          "State": "VA",
          "Hispanic": 0.0000648803,
          "NA": 0.000884173,
          "Asian": 0,
          "Pacific": 0,
          "Black": 0.000196886,
          "White": 0.000161844
        },
        {
          "State": "VT",
          "Hispanic": 0,
          "NA": 0,
          "Asian": 0,
          "Pacific": 0,
          "Black": 0,
          "White": 0.00029369
        },
        {
          "State": "WA",
          "Hispanic": 0.002209235,
          "NA": 0.003286826,
          "Asian": 0.001272359,
          "Pacific": 0.003662089,
          "Black": 0.003413108,
          "White": 0.002311444
        },
        {
          "State": "WI",
          "Hispanic": 0.000710047,
          "NA": 0.00124533,
          "Asian": 0.000299321,
          "Pacific": 0,
          "Black": 0.001357707,
          "White": 0.000474929
        },
        {
          "State": "WV",
          "Hispanic": 0,
          "NA": 0,
          "Asian": 0,
          "Pacific": 0,
          "Black": 0,
          "White": 0.000138613
        },
        {
          "State": "WY",
          "Hispanic": 0.00077997,
          "NA": 0,
          "Asian": 0,
          "Pacific": 0,
          "Black": 0,
          "White": 0.000767036
        }
      ],
    "EXPZT":[
        {
          "State": "AK",
          "Hispanic": 0,
          "NA": 0,
          "Asian": 0,
          "Pacific": 0,
          "Black": 0,
          "White": 0
        },
        {
          "State": "AL",
          "Hispanic": 0,
          "NA": 0,
          "Asian": 0.000179727,
          "Pacific": 0.001752848,
          "Black": 0.000448961,
          "White": 0.000147505
        },
        {
          "State": "AR",
          "Hispanic": 0.000234951,
          "NA": 0,
          "Asian": 0.00025025,
          "Pacific": 0.001346257,
          "Black": 0.000660462,
          "White": 0.000402047
        },
        {
          "State": "AZ",
          "Hispanic": 0.000071399,
          "NA": 0.000110756,
          "Asian": 0.000123369,
          "Pacific": 0,
          "Black": 0.000132499,
          "White": 0.0000468232
        },
        {
          "State": "CA",
          "Hispanic": 0.000216093,
          "NA": 0.000546788,
          "Asian": 0.000122127,
          "Pacific": 0.000419659,
          "Black": 0.000472203,
          "White": 0.000251747
        },
        {
          "State": "CO",
          "Hispanic": 0.0000766021,
          "NA": 0,
          "Asian": 0,
          "Pacific": 0,
          "Black": 0,
          "White": 0.0000328678
        },
        {
          "State": "CT",
          "Hispanic": 0.000551,
          "NA": 0.001006036,
          "Asian": 0.000148798,
          "Pacific": 0,
          "Black": 0.001101274,
          "White": 0.00032327
        },
        {
          "State": "DC",
          "Hispanic": 0.000156838,
          "NA": 0,
          "Asian": 0,
          "Pacific": 0,
          "Black": 0.000137613,
          "White": 0
        },
        {
          "State": "DE",
          "Hispanic": 0.0000905674,
          "NA": 0,
          "Asian": 0,
          "Pacific": 0,
          "Black": 0.000715671,
          "White": 0.0000630726
        },
        {
          "State": "FL",
          "Hispanic": 0.0000341338,
          "NA": 0.000381388,
          "Asian": 0.0000270059,
          "Pacific": 0,
          "Black": 0.0000828927,
          "White": 0.000104184
        },
        {
          "State": "GA",
          "Hispanic": 0.000260927,
          "NA": 0.00043573,
          "Asian": 0.0000596917,
          "Pacific": 0,
          "Black": 0.000530828,
          "White": 0.000220808
        },
        {
          "State": "HI",
          "Hispanic": 0.000181851,
          "NA": 0,
          "Asian": 0.000181449,
          "Pacific": 0.000467147,
          "Black": 0,
          "White": 0
        },
        {
          "State": "IA",
          "Hispanic": 0.000077824,
          "NA": 0,
          "Asian": 0,
          "Pacific": 0,
          "Black": 0.000415354,
          "White": 0.000172322
        },
        {
          "State": "ID",
          "Hispanic": 0.000294221,
          "NA": 0,
          "Asian": 0.000507872,
          "Pacific": 0.001554002,
          "Black": 0,
          "White": 0.000195619
        },
        {
          "State": "IL",
          "Hispanic": 0.000206729,
          "NA": 0.000843645,
          "Asian": 0.0000822893,
          "Pacific": 0,
          "Black": 0.000409577,
          "White": 0.000255658
        },
        {
          "State": "IN",
          "Hispanic": 0.000210213,
          "NA": 0,
          "Asian": 0,
          "Pacific": 0,
          "Black": 0.000276354,
          "White": 0.000248957
        },
        {
          "State": "KS",
          "Hispanic": 0.000204541,
          "NA": 0,
          "Asian": 0.000143482,
          "Pacific": 0,
          "Black": 0.000337117,
          "White": 0.00017251
        },
        {
          "State": "KY",
          "Hispanic": 0.000193911,
          "NA": 0,
          "Asian": 0,
          "Pacific": 0,
          "Black": 0.000273452,
          "White": 0.000356946
        },
        {
          "State": "LA",
          "Hispanic": 0.0000934012,
          "NA": 0,
          "Asian": 0,
          "Pacific": 0,
          "Black": 0.000172719,
          "White": 0.000100077
        },
        {
          "State": "MA",
          "Hispanic": 0.0000116784,
          "NA": 0,
          "Asian": 0,
          "Pacific": 0,
          "Black": 0.0000473776,
          "White": 0.0000134362
        },
        {
          "State": "MD",
          "Hispanic": 0,
          "NA": 0,
          "Asian": 0,
          "Pacific": 0,
          "Black": 0.0000708156,
          "White": 0
        },
        {
          "State": "ME",
          "Hispanic": 0,
          "NA": 0,
          "Asian": 0,
          "Pacific": 0,
          "Black": 0,
          "White": 0.0000935728
        },
        {
          "State": "MI",
          "Hispanic": 0.000321357,
          "NA": 0.000160321,
          "Asian": 0,
          "Pacific": 0,
          "Black": 0.000394052,
          "White": 0.000190937
        },
        {
          "State": "MN",
          "Hispanic": 0.000311935,
          "NA": 0.000122941,
          "Asian": 0,
          "Pacific": 0.001626016,
          "Black": 0.000108131,
          "White": 0.000130765
        },
        {
          "State": "MO",
          "Hispanic": 0.0000731342,
          "NA": 0,
          "Asian": 0,
          "Pacific": 0,
          "Black": 0.0000939062,
          "White": 0.000115981
        },
        {
          "State": "MS",
          "Hispanic": 0,
          "NA": 0.001390821,
          "Asian": 0,
          "Pacific": 0,
          "Black": 0.000327657,
          "White": 0.000118904
        },
        {
          "State": "MT",
          "Hispanic": 0,
          "NA": 0.00055966,
          "Asian": 0,
          "Pacific": 0,
          "Black": 0,
          "White": 0.000119836
        },
        {
          "State": "NC",
          "Hispanic": 0.0000158382,
          "NA": 0.000269445,
          "Asian": 0,
          "Pacific": 0,
          "Black": 0.0000500254,
          "White": 0.0000156153
        },
        {
          "State": "ND",
          "Hispanic": 0,
          "NA": 0.00038157,
          "Asian": 0,
          "Pacific": 0,
          "Black": 0,
          "White": 0.0000691986
        },
        {
          "State": "NE",
          "Hispanic": 0.000261721,
          "NA": 0.00083316,
          "Asian": 0.000241051,
          "Pacific": 0,
          "Black": 0.00018031,
          "White": 0.000144889
        },
        {
          "State": "NH",
          "Hispanic": 0,
          "NA": 0,
          "Asian": 0,
          "Pacific": 0,
          "Black": 0,
          "White": 0.0000760297
        },
        {
          "State": "NJ",
          "Hispanic": 0.0000114707,
          "NA": 0,
          "Asian": 0,
          "Pacific": 0,
          "Black": 0.0000550724,
          "White": 0.0000125287
        },
        {
          "State": "NM",
          "Hispanic": 0.000130328,
          "NA": 0,
          "Asian": 0,
          "Pacific": 0,
          "Black": 0,
          "White": 0.0000995211
        },
        {
          "State": "NV",
          "Hispanic": 0.001117244,
          "NA": 0.000824742,
          "Asian": 0.001316605,
          "Pacific": 0.001503986,
          "Black": 0.003465326,
          "White": 0.000848896
        },
        {
          "State": "NY",
          "Hispanic": 0.0000255918,
          "NA": 0.000104553,
          "Asian": 0,
          "Pacific": 0,
          "Black": 0.0000686766,
          "White": 0.0000359847
        },
        {
          "State": "OH",
          "Hispanic": 0.000572924,
          "NA": 0,
          "Asian": 0.000159477,
          "Pacific": 0,
          "Black": 0.000877597,
          "White": 0.000272012
        },
        {
          "State": "OK",
          "Hispanic": 0.000307954,
          "NA": 0.000672302,
          "Asian": 0.00028748,
          "Pacific": 0.000734484,
          "Black": 0.000401271,
          "White": 0.000463533
        },
        {
          "State": "OR",
          "Hispanic": 0.000170446,
          "NA": 0.000689814,
          "Asian": 0.000173198,
          "Pacific": 0.000441891,
          "Black": 0,
          "White": 0.000146172
        },
        {
          "State": "PA",
          "Hispanic": 0.000222821,
          "NA": 0.000523149,
          "Asian": 0.0000627362,
          "Pacific": 0,
          "Black": 0.000308237,
          "White": 0.000191691
        },
        {
          "State": "RI",
          "Hispanic": 0,
          "NA": 0,
          "Asian": 0,
          "Pacific": 0,
          "Black": 0,
          "White": 0
        },
        {
          "State": "SC",
          "Hispanic": 0.000217564,
          "NA": 0.00129408,
          "Asian": 0,
          "Pacific": 0,
          "Black": 0.000551914,
          "White": 0.000253152
        },
        {
          "State": "SD",
          "Hispanic": 0,
          "NA": 0.000386922,
          "Asian": 0,
          "Pacific": 0,
          "Black": 0.0004865,
          "White": 0.0000578732
        },
        {
          "State": "TN",
          "Hispanic": 0.00195882,
          "NA": 0.00164271,
          "Asian": 0.000619707,
          "Pacific": 0.005517241,
          "Black": 0.002403249,
          "White": 0.001068966
        },
        {
          "State": "TX",
          "Hispanic": 0.000238424,
          "NA": 0.000264015,
          "Asian": 0.0000651687,
          "Pacific": 0.000217085,
          "Black": 0.000328893,
          "White": 0.000184877
        },
        {
          "State": "UT",
          "Hispanic": 0.0000743225,
          "NA": 0.000266134,
          "Asian": 0,
          "Pacific": 0,
          "Black": 0.000634786,
          "White": 0.0000516407
        },
        {
          "State": "VA",
          "Hispanic": 0.0000973204,
          "NA": 0.000442087,
          "Asian": 0,
          "Pacific": 0,
          "Black": 0.000220648,
          "White": 0.000149513
        },
        {
          "State": "VT",
          "Hispanic": 0,
          "NA": 0,
          "Asian": 0,
          "Pacific": 0,
          "Black": 0,
          "White": 0.0000800972
        },
        {
          "State": "WA",
          "Hispanic": 0.00239906,
          "NA": 0.00174403,
          "Asian": 0.000975887,
          "Pacific": 0.001664586,
          "Black": 0.002397302,
          "White": 0.002064082
        },
        {
          "State": "WI",
          "Hispanic": 0.000162296,
          "NA": 0.000177904,
          "Asian": 0,
          "Pacific": 0,
          "Black": 0.000121224,
          "White": 0.000136157
        },
        {
          "State": "WV",
          "Hispanic": 0,
          "NA": 0,
          "Asian": 0,
          "Pacific": 0,
          "Black": 0.001117229,
          "White": 0.000712868
        },
        {
          "State": "WY",
          "Hispanic": 0.000155994,
          "NA": 0.000530363,
          "Asian": 0,
          "Pacific": 0,
          "Black": 0,
          "White": 0.000403703
        }
      ],
    "REF":[
        {
          "State": "AK",
          "Hispanic": 0.00248279,
          "NA": 0.005176653,
          "Asian": 0.001007811,
          "Pacific": 0.003284072,
          "Black": 0.004217432,
          "White": 0.001700221
        },
        {
          "State": "AL",
          "Hispanic": 0.001211977,
          "NA": 0.00235426,
          "Asian": 0.001078361,
          "Pacific": 0.001752848,
          "Black": 0.003507506,
          "White": 0.001593543
        },
        {
          "State": "AR",
          "Hispanic": 0.002852971,
          "NA": 0.003388873,
          "Asian": 0.000500501,
          "Pacific": 0.004308024,
          "Black": 0.004155828,
          "White": 0.00185739
        },
        {
          "State": "AZ",
          "Hispanic": 0.003752412,
          "NA": 0.009008178,
          "Asian": 0.001542115,
          "Pacific": 0.00359955,
          "Black": 0.005747126,
          "White": 0.002064678
        },
        {
          "State": "CA",
          "Hispanic": 0.003474937,
          "NA": 0.004970797,
          "Asian": 0.001415238,
          "Pacific": 0.004756132,
          "Black": 0.008551511,
          "White": 0.002223986
        },
        {
          "State": "CO",
          "Hispanic": 0.005881706,
          "NA": 0.008569454,
          "Asian": 0.002900909,
          "Pacific": 0.002275313,
          "Black": 0.010848361,
          "White": 0.003654486
        },
        {
          "State": "CT",
          "Hispanic": 0.004148705,
          "NA": 0.005030181,
          "Asian": 0.001339186,
          "Pacific": 0.002398082,
          "Black": 0.005955572,
          "White": 0.001969613
        },
        {
          "State": "DC",
          "Hispanic": 0.00086261,
          "NA": 0,
          "Asian": 0,
          "Pacific": 0,
          "Black": 0.002459834,
          "White": 0
        },
        {
          "State": "DE",
          "Hispanic": 0.007652946,
          "NA": 0.015267176,
          "Asian": 0.004651163,
          "Pacific": 0.003676471,
          "Black": 0.013066765,
          "White": 0.005345401
        },
        {
          "State": "FL",
          "Hispanic": 0.003845747,
          "NA": 0.010488177,
          "Asian": 0.002619568,
          "Pacific": 0.005446623,
          "Black": 0.009484838,
          "White": 0.004487235
        },
        {
          "State": "GA",
          "Hispanic": 0.001970581,
          "NA": 0.005882353,
          "Asian": 0.000999836,
          "Pacific": 0.004428044,
          "Black": 0.004318521,
          "White": 0.001941726
        },
        {
          "State": "HI",
          "Hispanic": 0.002000364,
          "NA": 0.006097561,
          "Asian": 0.002141094,
          "Pacific": 0.004294159,
          "Black": 0.004415011,
          "White": 0.002601057
        },
        {
          "State": "IA",
          "Hispanic": 0.004416514,
          "NA": 0.008659794,
          "Asian": 0.00281917,
          "Pacific": 0.007246377,
          "Black": 0.013014434,
          "White": 0.003531324
        },
        {
          "State": "ID",
          "Hispanic": 0.00337374,
          "NA": 0.008349813,
          "Asian": 0.001015744,
          "Pacific": 0.007770008,
          "Black": 0.004110393,
          "White": 0.002045108
        },
        {
          "State": "IL",
          "Hispanic": 0.003817716,
          "NA": 0.006186727,
          "Asian": 0.00128577,
          "Pacific": 0.001948685,
          "Black": 0.006217611,
          "White": 0.00177344
        },
        {
          "State": "IN",
          "Hispanic": 0.001646667,
          "NA": 0.002667556,
          "Asian": 0.000351664,
          "Pacific": 0.001845018,
          "Black": 0.003545231,
          "White": 0.001713493
        },
        {
          "State": "KS",
          "Hispanic": 0.003046581,
          "NA": 0.005890506,
          "Asian": 0.001721788,
          "Pacific": 0,
          "Black": 0.009326891,
          "White": 0.002484137
        },
        {
          "State": "KY",
          "Hispanic": 0.00176944,
          "NA": 0.00310559,
          "Asian": 0.000874432,
          "Pacific": 0,
          "Black": 0.003404476,
          "White": 0.000933264
        },
        {
          "State": "LA",
          "Hispanic": 0.00154112,
          "NA": 0.002905393,
          "Asian": 0.000347614,
          "Pacific": 0,
          "Black": 0.002383517,
          "White": 0.00097348
        },
        {
          "State": "MA",
          "Hispanic": 0.001880215,
          "NA": 0,
          "Asian": 0.000532739,
          "Pacific": 0,
          "Black": 0.001776662,
          "White": 0.000760825
        },
        {
          "State": "MD",
          "Hispanic": 0.00422329,
          "NA": 0.00701307,
          "Asian": 0.000857265,
          "Pacific": 0.003399433,
          "Black": 0.006090142,
          "White": 0.001820344
        },
        {
          "State": "ME",
          "Hispanic": 0.003309432,
          "NA": 0.001387925,
          "Asian": 0.001411931,
          "Pacific": 0,
          "Black": 0.003674121,
          "White": 0.003119093
        },
        {
          "State": "MI",
          "Hispanic": 0.001767463,
          "NA": 0.00488978,
          "Asian": 0.000560381,
          "Pacific": 0.000899281,
          "Black": 0.002779857,
          "White": 0.001401807
        },
        {
          "State": "MN",
          "Hispanic": 0.0057968,
          "NA": 0.013093189,
          "Asian": 0.003170274,
          "Pacific": 0.003252033,
          "Black": 0.012175606,
          "White": 0.002800694
        },
        {
          "State": "MO",
          "Hispanic": 0.003620141,
          "NA": 0.007073386,
          "Asian": 0.000973763,
          "Pacific": 0.002873563,
          "Black": 0.00890767,
          "White": 0.003247463
        },
        {
          "State": "MS",
          "Hispanic": 0.00125539,
          "NA": 0,
          "Asian": 0.000373762,
          "Pacific": 0,
          "Black": 0.002879283,
          "White": 0.001641796
        },
        {
          "State": "MT",
          "Hispanic": 0.005395683,
          "NA": 0.013879561,
          "Asian": 0.003055768,
          "Pacific": 0,
          "Black": 0.013071895,
          "White": 0.00425419
        },
        {
          "State": "NC",
          "Hispanic": 0.003151801,
          "NA": 0.00233519,
          "Asian": 0.001636696,
          "Pacific": 0.002944424,
          "Black": 0.005080078,
          "White": 0.00179055
        },
        {
          "State": "ND",
          "Hispanic": 0.007086286,
          "NA": 0.008299151,
          "Asian": 0.00103146,
          "Pacific": 0.008908686,
          "Black": 0.006750422,
          "White": 0.003021671
        },
        {
          "State": "NE",
          "Hispanic": 0.004257324,
          "NA": 0.009373047,
          "Asian": 0.002169459,
          "Pacific": 0,
          "Black": 0.005499459,
          "White": 0.002640718
        },
        {
          "State": "NH",
          "Hispanic": 0.003435037,
          "NA": 0.011444921,
          "Asian": 0.002372077,
          "Pacific": 0.007380074,
          "Black": 0.013757756,
          "White": 0.00621543
        },
        {
          "State": "NJ",
          "Hispanic": 0.00200164,
          "NA": 0.000799041,
          "Asian": 0.000609588,
          "Pacific": 0.000523697,
          "Black": 0.003446614,
          "White": 0.001162035
        },
        {
          "State": "NM",
          "Hispanic": 0.002162486,
          "NA": 0.008802817,
          "Asian": 0.001425856,
          "Pacific": 0.005943536,
          "Black": 0.003168659,
          "White": 0.002550227
        },
        {
          "State": "NV",
          "Hispanic": 0.003453764,
          "NA": 0.011958763,
          "Asian": 0.001548947,
          "Pacific": 0.005113551,
          "Black": 0.009180075,
          "White": 0.003726406
        },
        {
          "State": "NY",
          "Hispanic": 0.001757304,
          "NA": 0.002718386,
          "Asian": 0.000792184,
          "Pacific": 0.000501756,
          "Black": 0.003960351,
          "White": 0.001512992
        },
        {
          "State": "OH",
          "Hispanic": 0.001381759,
          "NA": 0.000586166,
          "Asian": 0.000823964,
          "Pacific": 0.001671542,
          "Black": 0.002165682,
          "White": 0.001188765
        },
        {
          "State": "OK",
          "Hispanic": 0.003215405,
          "NA": 0.003737209,
          "Asian": 0.002515452,
          "Pacific": 0.011751744,
          "Black": 0.007848865,
          "White": 0.003776932
        },
        {
          "State": "OR",
          "Hispanic": 0.001843918,
          "NA": 0.005173603,
          "Asian": 0.000519593,
          "Pacific": 0.002209456,
          "Black": 0.001726122,
          "White": 0.001594105
        },
        {
          "State": "PA",
          "Hispanic": 0.012750953,
          "NA": 0.010986137,
          "Asian": 0.004767954,
          "Pacific": 0.004119464,
          "Black": 0.022403783,
          "White": 0.004610898
        },
        {
          "State": "RI",
          "Hispanic": 0.010956088,
          "NA": 0.032286996,
          "Asian": 0.000444247,
          "Pacific": 0,
          "Black": 0.015475991,
          "White": 0.001463449
        },
        {
          "State": "SC",
          "Hispanic": 0.001243221,
          "NA": 0.003235199,
          "Asian": 0.001503885,
          "Pacific": 0.002939015,
          "Black": 0.004834917,
          "White": 0.002179642
        },
        {
          "State": "SD",
          "Hispanic": 0.008430518,
          "NA": 0.014380602,
          "Asian": 0.003296251,
          "Pacific": 0,
          "Black": 0.010946242,
          "White": 0.003655655
        },
        {
          "State": "TN",
          "Hispanic": 0.002671119,
          "NA": 0.00164271,
          "Asian": 0.002065689,
          "Pacific": 0.009655172,
          "Black": 0.003485155,
          "White": 0.002927563
        },
        {
          "State": "TX",
          "Hispanic": 0.002532268,
          "NA": 0.002640148,
          "Asian": 0.000567899,
          "Pacific": 0.002170846,
          "Black": 0.004248577,
          "White": 0.00140679
        },
        {
          "State": "UT",
          "Hispanic": 0.004254963,
          "NA": 0.006254158,
          "Asian": 0.001753617,
          "Pacific": 0.003577645,
          "Black": 0.00740584,
          "White": 0.001938512
        },
        {
          "State": "VA",
          "Hispanic": 0.007466641,
          "NA": 0.009725906,
          "Asian": 0.002300972,
          "Pacific": 0.003835827,
          "Black": 0.016063166,
          "White": 0.006376672
        },
        {
          "State": "VT",
          "Hispanic": 0.002708192,
          "NA": 0,
          "Asian": 0.003076923,
          "Pacific": 0,
          "Black": 0.007575758,
          "White": 0.002095876
        },
        {
          "State": "WA",
          "Hispanic": 0.002657544,
          "NA": 0.003420982,
          "Asian": 0.000951181,
          "Pacific": 0.002829796,
          "Black": 0.00408354,
          "White": 0.001400627
        },
        {
          "State": "WI",
          "Hispanic": 0.006045544,
          "NA": 0.013431774,
          "Asian": 0.002454428,
          "Pacific": 0.004950495,
          "Black": 0.010049459,
          "White": 0.005136692
        },
        {
          "State": "WV",
          "Hispanic": 0.002619515,
          "NA": 0,
          "Asian": 0,
          "Pacific": 0,
          "Black": 0.003670896,
          "White": 0.001912864
        },
        {
          "State": "WY",
          "Hispanic": 0.008033695,
          "NA": 0.013259082,
          "Asian": 0.006734007,
          "Pacific": 0.007751938,
          "Black": 0.016515277,
          "White": 0.0073474
        }
      ],
      "ARREST":[
        {
          "State": "AK",
          "Hispanic": 0,
          "NA": 0.0000647082,
          "Asian": 0,
          "Pacific": 0,
          "Black": 0,
          "White": 0.0000317798
        },
        {
          "State": "AL",
          "Hispanic": 0.000854344,
          "NA": 0.002017937,
          "Asian": 0.00053918,
          "Pacific": 0,
          "Black": 0.001872006,
          "White": 0.000585186
        },
        {
          "State": "AR",
          "Hispanic": 0.001762129,
          "NA": 0.000564812,
          "Asian": 0.00025025,
          "Pacific": 0.003769521,
          "Black": 0.002103317,
          "White": 0.000817384
        },
        {
          "State": "AZ",
          "Hispanic": 0.001285181,
          "NA": 0.002602773,
          "Asian": 0.000246738,
          "Pacific": 0.000899888,
          "Black": 0.001904667,
          "White": 0.000680051
        },
        {
          "State": "CA",
          "Hispanic": 0.000405582,
          "NA": 0.000894743,
          "Asian": 0.000170978,
          "Pacific": 0.000699431,
          "Black": 0.001288322,
          "White": 0.000277584
        },
        {
          "State": "CO",
          "Hispanic": 0.000406324,
          "NA": 0.001105736,
          "Asian": 0.000141508,
          "Pacific": 0.001516875,
          "Black": 0.00090403,
          "White": 0.000215695
        },
        {
          "State": "CT",
          "Hispanic": 0.00308722,
          "NA": 0.004024145,
          "Asian": 0.000669593,
          "Pacific": 0,
          "Black": 0.00426019,
          "White": 0.001173103
        },
        {
          "State": "DC",
          "Hispanic": 0.00086261,
          "NA": 0,
          "Asian": 0,
          "Pacific": 0,
          "Black": 0.001823374,
          "White": 0
        },
        {
          "State": "DE",
          "Hispanic": 0.001992483,
          "NA": 0,
          "Asian": 0.000775194,
          "Pacific": 0,
          "Black": 0.003532182,
          "White": 0.001766032
        },
        {
          "State": "FL",
          "Hispanic": 0.000351579,
          "NA": 0.001334859,
          "Asian": 0.0000810176,
          "Pacific": 0.000363108,
          "Black": 0.000950078,
          "White": 0.000329003
        },
        {
          "State": "GA",
          "Hispanic": 0.001316317,
          "NA": 0.003050109,
          "Asian": 0.000567071,
          "Pacific": 0.001476015,
          "Black": 0.002700032,
          "White": 0.000974313
        },
        {
          "State": "HI",
          "Hispanic": 0.001818512,
          "NA": 0.006097561,
          "Asian": 0.002032225,
          "Pacific": 0.003737176,
          "Black": 0.003863135,
          "White": 0.002430496
        },
        {
          "State": "IA",
          "Hispanic": 0.001731585,
          "NA": 0.004123711,
          "Asian": 0.001288764,
          "Pacific": 0.00942029,
          "Black": 0.008791665,
          "White": 0.001435163
        },
        {
          "State": "ID",
          "Hispanic": 0.000392295,
          "NA": 0.001757855,
          "Asian": 0,
          "Pacific": 0,
          "Black": 0,
          "White": 0.00032455
        },
        {
          "State": "IL",
          "Hispanic": 0.00119207,
          "NA": 0.002530934,
          "Asian": 0.000473163,
          "Pacific": 0.001299123,
          "Black": 0.002778868,
          "White": 0.000669966
        },
        {
          "State": "IN",
          "Hispanic": 0.001129894,
          "NA": 0.003334445,
          "Asian": 0.000263748,
          "Pacific": 0.001845018,
          "Black": 0.002787231,
          "White": 0.000944368
        },
        {
          "State": "KS",
          "Hispanic": 0.000678214,
          "NA": 0.001039501,
          "Asian": 0.000143482,
          "Pacific": 0,
          "Black": 0.001994606,
          "White": 0.000567713
        },
        {
          "State": "KY",
          "Hispanic": 0.000387822,
          "NA": 0.001552795,
          "Asian": 0,
          "Pacific": 0,
          "Black": 0.001572349,
          "White": 0.000308609
        },
        {
          "State": "LA",
          "Hispanic": 0.001167515,
          "NA": 0.000726348,
          "Asian": 0.000347614,
          "Pacific": 0,
          "Black": 0.002163693,
          "White": 0.000576203
        },
        {
          "State": "MA",
          "Hispanic": 0.000572239,
          "NA": 0,
          "Asian": 0.0000968617,
          "Pacific": 0,
          "Black": 0.000497465,
          "White": 0.000112528
        },
        {
          "State": "MD",
          "Hispanic": 0.001110647,
          "NA": 0.003187759,
          "Asian": 0.000142878,
          "Pacific": 0.002266289,
          "Black": 0.002719963,
          "White": 0.001119541
        },
        {
          "State": "ME",
          "Hispanic": 0,
          "NA": 0,
          "Asian": 0.000705965,
          "Pacific": 0,
          "Black": 0,
          "White": 0.000224575
        },
        {
          "State": "MI",
          "Hispanic": 0.000374916,
          "NA": 0.000480962,
          "Asian": 0.0000400272,
          "Pacific": 0.000899281,
          "Black": 0.00093856,
          "White": 0.000176545
        },
        {
          "State": "MN",
          "Hispanic": 0.001117769,
          "NA": 0.003073519,
          "Asian": 0.000102267,
          "Pacific": 0,
          "Black": 0.002000433,
          "White": 0.000766384
        },
        {
          "State": "MO",
          "Hispanic": 0.000585073,
          "NA": 0.00132626,
          "Asian": 0.000432783,
          "Pacific": 0.001436782,
          "Black": 0.003306838,
          "White": 0.000700346
        },
        {
          "State": "MS",
          "Hispanic": 0.000982479,
          "NA": 0,
          "Asian": 0.000373762,
          "Pacific": 0,
          "Black": 0.001671049,
          "White": 0.000841478
        },
        {
          "State": "MT",
          "Hispanic": 0.00147155,
          "NA": 0.006548019,
          "Asian": 0,
          "Pacific": 0,
          "Black": 0,
          "White": 0.001087087
        },
        {
          "State": "NC",
          "Hispanic": 0.000233613,
          "NA": 0.00017963,
          "Asian": 0.0000419666,
          "Pacific": 0,
          "Black": 0.0005903,
          "White": 0.000111909
        },
        {
          "State": "ND",
          "Hispanic": 0.001250521,
          "NA": 0.003529524,
          "Asian": 0,
          "Pacific": 0.004454343,
          "Black": 0.002625164,
          "White": 0.000738118
        },
        {
          "State": "NE",
          "Hispanic": 0.000575786,
          "NA": 0.00166632,
          "Asian": 0,
          "Pacific": 0,
          "Black": 0.00054093,
          "White": 0.000411298
        },
        {
          "State": "NH",
          "Hispanic": 0.000404122,
          "NA": 0.00286123,
          "Asian": 0.000677736,
          "Pacific": 0,
          "Black": 0.004316159,
          "White": 0.000855334
        },
        {
          "State": "NJ",
          "Hispanic": 0.000811553,
          "NA": 0,
          "Asian": 0.000163548,
          "Pacific": 0,
          "Black": 0.001560385,
          "White": 0.000366464
        },
        {
          "State": "NM",
          "Hispanic": 0.000381331,
          "NA": 0.00096547,
          "Asian": 0,
          "Pacific": 0,
          "Black": 0.00028806,
          "White": 0.000447845
        },
        {
          "State": "NV",
          "Hispanic": 0.001658011,
          "NA": 0.006185567,
          "Asian": 0.000851921,
          "Pacific": 0.002707174,
          "Black": 0.003485592,
          "White": 0.001404424
        },
        {
          "State": "NY",
          "Hispanic": 0.0000881496,
          "NA": 0.00031366,
          "Asian": 0.0000247557,
          "Pacific": 0,
          "Black": 0.000405816,
          "White": 0.000197916
        },
        {
          "State": "OH",
          "Hispanic": 0.000449352,
          "NA": 0,
          "Asian": 0.000159477,
          "Pacific": 0,
          "Black": 0.000746665,
          "White": 0.00028708
        },
        {
          "State": "OK",
          "Hispanic": 0.000715541,
          "NA": 0.001166642,
          "Asian": 0.00057496,
          "Pacific": 0.002570694,
          "Black": 0.002905204,
          "White": 0.000898452
        },
        {
          "State": "OR",
          "Hispanic": 0.000302155,
          "NA": 0.000229938,
          "Asian": 0.0000865988,
          "Pacific": 0.000441891,
          "Black": 0.000143843,
          "White": 0.000270281
        },
        {
          "State": "PA",
          "Hispanic": 0.003141781,
          "NA": 0.002615747,
          "Asian": 0.000674415,
          "Pacific": 0.001029866,
          "Black": 0.004604052,
          "White": 0.001314329
        },
        {
          "State": "RI",
          "Hispanic": 0.001850492,
          "NA": 0.00896861,
          "Asian": 0,
          "Pacific": 0,
          "Black": 0.003597122,
          "White": 0.000499714
        },
        {
          "State": "SC",
          "Hispanic": 0.000839174,
          "NA": 0.00064704,
          "Asian": 0.000501295,
          "Pacific": 0.001469508,
          "Black": 0.003394649,
          "White": 0.001372086
        },
        {
          "State": "SD",
          "Hispanic": 0.002248138,
          "NA": 0.005029986,
          "Asian": 0,
          "Pacific": 0,
          "Black": 0,
          "White": 0.000713769
        },
        {
          "State": "TN",
          "Hispanic": 0.000812465,
          "NA": 0.000821355,
          "Asian": 0.000206569,
          "Pacific": 0.002758621,
          "Black": 0.001928807,
          "White": 0.000889505
        },
        {
          "State": "TX",
          "Hispanic": 0.001378683,
          "NA": 0.001144064,
          "Asian": 0.000288604,
          "Pacific": 0.001302507,
          "Black": 0.002674696,
          "White": 0.000634812
        },
        {
          "State": "UT",
          "Hispanic": 0.000222968,
          "NA": 0.000266134,
          "Asian": 0,
          "Pacific": 0,
          "Black": 0.000423191,
          "White": 0.000139033
        },
        {
          "State": "VA",
          "Hispanic": 0.000378468,
          "NA": 0,
          "Asian": 0.0000467202,
          "Pacific": 0,
          "Black": 0.00045148,
          "White": 0.000241996
        },
        {
          "State": "VT",
          "Hispanic": 0,
          "NA": 0,
          "Asian": 0,
          "Pacific": 0,
          "Black": 0.002840909,
          "White": 0.000440535
        },
        {
          "State": "WA",
          "Hispanic": 0.001264151,
          "NA": 0.000939093,
          "Asian": 0.000024706,
          "Pacific": 0.000332917,
          "Black": 0.000203161,
          "White": 0.000688027
        },
        {
          "State": "WI",
          "Hispanic": 0.001430238,
          "NA": 0.001956947,
          "Asian": 0.000299321,
          "Pacific": 0.001650165,
          "Black": 0.005115648,
          "White": 0.001121676
        },
        {
          "State": "WV",
          "Hispanic": 0.000436586,
          "NA": 0,
          "Asian": 0,
          "Pacific": 0,
          "Black": 0.001835448,
          "White": 0.000186138
        },
        {
          "State": "WY",
          "Hispanic": 0.000311988,
          "NA": 0.002651816,
          "Asian": 0,
          "Pacific": 0,
          "Black": 0,
          "White": 0.000403703
        }
      ]
}